{
  "229753": "Two giraffes are standing by a palm tree.  .\n",
  "229849": "A tennis player is jumping and reaching to hit the ball.\n",
  "229858": "A baby deer and a large deer are standing in the woods. .\n",
  "229948": "there are two horses that are pulling a carriage.\n",
  "229997": "A black bear is surrounded by black birds on grass.\n",
  "230008": "A police man on a motorcycle is idle in front of a bush.\n",
  "230166": "A herd of sheep grazing in a field.\n",
  "230362": "Several sailboats are docked at a lake under cloudy skies.\n",
  "230450": "The street is lined with parking meters. .\n",
  "230819": "A man in a wetsuit that is riding on a surfboard.\n",
  "230983": "The boy jumps with a skateboard over the garbage can.\n",
  "230993": "Two women walk outside, both holding up umbrellas.\n",
  "231088": "Several umbrellas of different colors are hanging in the sun.\n",
  "231097": "Broccoli, carrots and a small amount of potatoes on a plate.\n",
  "231125": "Pans of potatoes and a  person wearing a red apron in a commercial kitchen.\n",
  "231169": "A train traveling down train tracks in the countryside.\n",
  "231237": "A bunch of small red flowers in a barnacle encrusted clay vase .\n",
  "231339": "a little girl looking inside the refrigerator. .\n",
  "231508": "A man in black jersey pitching in baseball game.\n",
  "231527": "some cut up oranges and jars and a wooden knife.\n",
  "231549": "A very fancy modern bedroom with a large mural over the bed.\n",
  "231580": "A man stands and holds his hands out in front of him.\n",
  "231747": "Several museum displays of baseball uniforms and bats.\n",
  "231822": "Cafeteria lunch fare is a balanced meal plus dessert.\n",
  "231831": "A cat is looking at a cluttered computer desk.\n",
  "231879": "a person holding up a child with a cake .\n",
  "232088": "A den with a couch, ottoman, television and windows.\n",
  "232244": "An elephant walking draped with a colorful blanket.\n",
  "232348": "A toaster and blender sitting on a counter top.\n",
  "232489": "Two slices of pizza are sitting on a paper plate.\n",
  "232538": "A train is pulling into the train station.\n",
  "232563": "A man holding a black and white umbrella.\n",
  "232646": "An icy snow covered road overlooking a body of water.\n",
  "232649": "a woman taking a picture in a bathroom mirror and a toilet and sink.\n",
  "232684": "A person sitting next to a laptop in a dark room.\n",
  "232692": "The man is about to perform a stunt in the water.\n",
  "233033": "A deck with  a chair and a table with umbrella on it.\n",
  "233139": "Two stone clocks are sitting on a shelf.\n",
  "233238": "A group of people eating food at an outdoor picinic.\n",
  "233370": "Someone who is laying down under a suitcase.\n",
  "233567": "Black and white sheep in hay next to wooden fence.\n",
  "233727": "A bus drives on a paved road with markings.\n",
  "233771": "A group of people walking on the street in a city.\n",
  "233825": "A view of a living room with large windows.\n",
  "234366": "A clock tower sculpture on roundabout next to a building.\n",
  "234413": "A toilet right next to a shower stall. .\n",
  "234526": "two children are feeding a giraffe and trees.\n",
  "234607": "A couple fighting each other over a wii remote control.\n",
  "234660": "Two white passenger trains are parked on the tracks, side by side.\n",
  "234757": "Some posts and the top of a bench are in high water.\n",
  "234779": "A sandwich is sitting in a white plate on top of a wood table.\n",
  "234807": "Horses are standing in a field outside of a crumbling castle.\n",
  "235057": "A giraffe drinking water with a long tongue.\n",
  "235064": "A bear walking across a stone wall near trees.\n",
  "235241": "a woman tries to catch a frisbe as a man watches on.\n",
  "235252": "an image of a herd of giraffes herding in the wilderness.\n",
  "235399": "Bull dog sitting on a furniture pad in a truck.\n",
  "235778": "A boy hangs up paper kites on a string. .\n",
  "235784": "a kid stands in the snow on his skiis.\n",
  "235836": "A child playing with a plastic bat and ball in a yard next to a garage. .\n",
  "235857": "some cows are eating grass in a field.\n",
  "236166": "Man cradling dog dressed in uniform with it's head resting on his shoulder.\n",
  "236308": "Multiple skiers travelling across a vast expanse of snow covered land towards a mountain.\n",
  "236412": "A cheese pizza pie is in the serving dish on the counter.\n",
  "236426": "A tennis player is jumping in the air at a tennis match.\n",
  "236592": "The dog stares at the food inside the oven.\n",
  "236599": "A fence with a bunch of kites attached to it.\n",
  "236690": "A white bird fly's in the air above the blue water.\n",
  "236721": "This tray includes several different items for a full breakfast.\n",
  "236730": "a close up of a giraffe in an outdoor area.\n",
  "236784": "Two dogs are lying on the brown couch. .\n",
  "236845": "there is a street sign that has been written on.\n",
  "236914": "Two teddy bears sitting at a table with honey.\n",
  "237071": "A man running with a racket trying to .hit a tennis ball.\n",
  "237118": "A man takes a photo of his reflection in a public restroom.\n",
  "237316": "A white small bathroom showing the toilet bowl and sink with beige tiles.\n",
  "237517": "Food set out on an outdoor picnic table.\n",
  "237864": "an elephant and a dog on a dirt field with trees in the background.\n",
  "237928": "A small kitchen is shown it has many appliances.\n",
  "237984": "A green chair is next to a long bench.\n",
  "238013": "The sun shines as the man plays tennis at a tennis court.\n",
  "238039": "A sheep being walked on a leash on a path. .\n",
  "238410": "a group of people sitting around a long table .\n",
  "238866": "A couple dozen of glazed donuts on a wire rack.\n",
  "239041": "A bathroom with purple walls and two mirrors.\n",
  "239274": "A pontoon boat ferry full of passengers pushes off from shore. .\n",
  "239318": "A laptop computer with a laptop keyboard on top of it.\n",
  "239347": "a man and a woman are laying in a bed.\n",
  "239537": "A man in white shirt and shorts playing a game of tennis.\n",
  "239627": "A double sink full of dirty cups and spoons.\n",
  "239717": "Server smiling while carrying food inside a busy restaurant.\n",
  "239773": "A baseball player with a bat watching the baseball.\n",
  "239843": "a street sign on top of a stop sign.\n",
  "239857": "A man holding a neon frisbee in his right hand.\n",
  "240023": "An athlete wiping sweat from his brow with his shirt.\n",
  "240049": "a woman and a baby look at giraffes at the zoo.\n",
  "240250": "A woman sitting at a table with two pizzas and a plate on it.\n",
  "240754": "A small cow in a enclosure with straw on the floor. .\n",
  "240767": "This blurry picture shows the side of a brick building.\n",
  "240940": "A cat watches cars racing on a television.\n",
  "241297": "Train drives down the tracks along the treeline.\n",
  "241319": "Two toothbrushes each in a glass on the sink.\n",
  "241326": "a cat sitting on a couch with a dog in front of it.\n",
  "241602": "A mirror that is hanging above a sink.\n",
  "241668": "A bride is with a long red haired person with cake.\n",
  "241677": "a bunch of people on camels walk up some stairs .\n",
  "242060": "A plate of cupcakes on a napkin with spoons and drink glasses.\n",
  "242287": "A bicycle that is leaning against a wall.\n",
  "242411": "A building in the city with a clock on the building. .\n",
  "242678": "A horseback rider competing in an obstacle course event.\n",
  "242724": "a couple of women ride horses through some water .\n",
  "242934": "A black leather sofa in a large living room.\n",
  "242946": "A group of women are sitting at a table with plates of food and chopsticks.\n",
  "243034": "A large clock tower sits in front of a body of water.\n",
  "243075": "A polar bear in a polar bear enclosure at a zoo looking up. .\n",
  "243148": "A lady seems to be attending to a fallen toddler. .\n",
  "243199": "A plaid comforter with a laptop sitting on it.\n",
  "243204": "A person bundled up while frying something on the stove indoors.\n",
  "243344": "A long haired cat sitting on a refrigerator.\n",
  "243495": "A toilet in a small room with a two-roll dispenser for toilet paper.\n",
  "243626": "A fork, a pork chop, green beans, an egg and parsley on a white plate.\n",
  "243867": "A bus parked along the side of a busy street.\n",
  "243989": "THERE ARE PEOPLE STADING ON THE STREET WITH SKATE BOARD.\n",
  "244019": "A fire hydrant in front of graffiti on a brick wall.\n",
  "244099": "A person riding a horse through a field.\n",
  "244181": "Cut hoagie sandwich and pie on paper plates.\n",
  "244379": "An intersection with a stoplight on a roadway that has no vehicles traveling on it.\n",
  "244411": "Green fields with shrubs and gentle rises and dips in the terrain has a large black cow standing on it, face-front, and a second one that is looking around at the other one.  .\n",
  "244496": "A man in a suit with a red tie that has a robot on it .\n",
  "244592": "Three zebras interacting in a zoo zebra enclosure.\n",
  "244750": "a man in glasses sits in front of some wine glasses .\n",
  "244833": "a yellow motorcycle and a green motorcycle behind some chairs.\n",
  "245026": "A woman in glasses holding up a cake with frosting.\n",
  "245102": "it is snowing near a staircase and some walls with a light.\n",
  "245173": "A tower building with a clock up high.\n",
  "245311": "Two adults working behind a counter displaying pastries.\n",
  "245320": "a guy riding his skate board on the sidewalk.\n",
  "245448": "Men in neon vests are in a parking lot with a motorcycle.\n",
  "245513": "An adult giraffe standing near a white duck in a field of grass.\n",
  "245576": "A cat sniffs the keyboard of a computer.\n",
  "245651": "2 tier cake with multicolored stars attached to it. .\n",
  "245764": "A cat is laying on a toilet seat.\n",
  "245915": "A herd of elephants is moving across a stream.\n",
  "246308": "A wooden desk topped with a laptop and monitor.\n",
  "246436": "A person slices a pizza fresh out of the oven.\n",
  "246454": "A little girl kneeling down to pet two dogs on a leash.\n",
  "246522": "A spire over a beautiful brick building behind red tiled roofs.\n",
  "246883": "two surfers walking on the beach carrying their surfboards.\n",
  "246963": "A group of people riding motorcycles on a road and stopping and a stop sign.\n",
  "246968": "A woman standing in a kitchen making food.\n",
  "247806": "A brick clock tower ascending towards the heavens.\n",
  "247838": "A herd of bison stroll by the snow covered banks of a stream.\n",
  "247917": "A little league baseball team in orange uniforms posing for a group picture. .\n",
  "248111": "the kitchen is white with brown counter tops and a white fridge.\n",
  "248112": "The man is swinging the tennis racket in the air. .\n",
  "248284": "A man and woman who are standing in the snow.\n",
  "248314": "desktop picture with laptop and food container full of food.\n",
  "248334": "A group of people riding on the back of a boat in a river.\n",
  "248400": "a kid is showing a pizza with a joke written inside the box cover.\n",
  "248616": "there are three pictures of a man hitting a tennis ball.\n",
  "248631": "A Windows laptop with a corded mouse on top of a counter.\n",
  "248752": "a man is holding a baseball bat at a game.\n",
  "248810": "a large giraffe that is next to a fence.\n",
  "248980": "A plate of food sitting on a table, it appears to be a salad.\n",
  "249025": "Two orange roses in a small vase with water. .\n",
  "249129": "There is a table set with stuffed animals.\n",
  "249180": "Men are walking up and down the stairs.\n",
  "249219": "A double decker tour bus with the logo \"SBS Transit\". .\n",
  "249550": "A bed made up with a flowered bedspread and pillows with a night stand.\n",
  "249643": "A train on its tracks with a Mannheim sign on the front.\n",
  "249786": "Person high up in the air doing ski tricks.\n",
  "250127": "a young woman is waiting in the rain.\n",
  "250137": "a person with her hand in her bag and holding an umbrella.\n",
  "250205": "Two heron are standing on some rocks near some water.\n",
  "250282": "A picture of a lot of girls and boys in front of a building. .\n",
  "250619": "A lady laying on a blanket on the beach under an umbrella.\n",
  "250758": "A zebra with a left side pose while standing in a field.\n",
  "250766": "A dinner plate with a colorful salad and grilled meat.\n",
  "250901": "Three people opening a wrapped sandwich out on the grass.\n",
  "251065": "A white toilet with a black seat sitting in a small stall.\n",
  "251119": "A sandwich with some strawberry yogurt and orange juice. .\n",
  "251140": "A manual or book about ten-speed bicycles .\n",
  "251537": "A table with cilantro, a carrot, celery, and garlic.\n",
  "251572": "A young dog relaxing with his or her human at the end of the day.\n",
  "251824": "A person is removing an object from the plastic casing.\n",
  "252216": "A white horse and a white llama in a grassy field. .\n",
  "252219": "People are walking on the street by a homeless person.\n",
  "252294": "A guy peeks out from behind a curtain.\n",
  "252332": "a close up of a stop sign with trees in the background.\n",
  "252507": "a man on skis standing on a snowy terrain .\n",
  "252559": "There is a lot of foot traffic on this street in the city.\n",
  "252701": "A boy riding waves on his surf board in the ocean. .\n",
  "252716": "A woman walking up to get the freeze bee.\n",
  "252776": "A man is about to serve a tennis ball.\n",
  "253002": "The side of a buss with a sign on it.\n",
  "253386": "A big dog next to a person's leg.\n",
  "253433": "A stuffed bear that is wearing a mask.\n",
  "253452": "A plate with creamy chicken and vegetables, a side of onion rings, a cup of coffee and a slice of cheesecake.\n",
  "253695": "a close up of a baseball player catching a ball.\n",
  "253742": "Several people holding umbrellas and standing next to deer.\n",
  "253819": "skateboarder does a jump off of the street corner.\n",
  "253835": "A woman and baby are waiting for the train.\n",
  "254016": "A machine that holds a lot of donuts and cooks them. .\n",
  "254368": "A person with a piece of pizza over a plate.\n",
  "254516": "A baseball player practicing his swing at a game.\n",
  "254814": "A crowded city street filled with motorcycle and car traffic. .\n",
  "255165": "A computer desk with two monitors and a laptop.\n",
  "255401": "This bathroom seems to be very dirty and old.\n",
  "255483": "A hand with scissors cutting into some sheets of paper.\n",
  "255536": "two people riding a motorcycle with chairs and umbrellas near by.\n",
  "255664": "A dog is opening his mouth to catch a Frisbee.\n",
  "255718": "A close up picture of a fire hydrant on a street.\n",
  "255747": "An open faced corn beef sandwich sits on a white plate.\n",
  "255749": "A man stands beside a bus in a snowy forest at night.\n",
  "255824": "A doughnut with a bite taken from it next to a cup.\n",
  "255912": "A sandwich sits on a white plate with a salad.\n",
  "255917": "Traffic stopped at an intersection waiting for the light to turn green.\n",
  "255965": "a stripped cat sitting near a brick wall.\n",
  "256192": "A yellow police motorcycle parked on a road near a large crowd behind a barrier.\n",
  "256195": "The train is on the tracks in the station. .\n",
  "256407": "This seems to be several glasses on an object. .\n",
  "256518": "A white plate topped with food next to a cup of coffee.\n",
  "256775": "Three children fly a kite along the beach.\n",
  "256868": "A man filming a person skateboarding on a wall.\n",
  "256916": "Four pans of pizza set on a long table.\n",
  "256941": "A bike with a basket attached to it is parked.\n",
  "257084": "A man who is on a skateboard on a ramp.\n",
  "257169": "this is a blow dryer in a bathroom.\n",
  "257370": "Two people playing a video game on a television.\n",
  "257478": "A baseball player signaling to another player or coach.\n",
  "257566": "People in a small boat traveling in water along a walkway.\n",
  "257624": "The young child is standing beside two soccer balls. .\n",
  "257865": "The older man is playing tennis on the court. .\n",
  "257896": "The guy is standing outside taking his picture in his suit. .\n",
  "258388": "The young man is practicing his tricks on his skateboard while the other is playing with fire.\n",
  "258541": "A man dressed in a shirt and tie standing in a lobby.\n",
  "258793": "a number of buildings in the distance .\n",
  "258883": "Several pieces of bread sitting on a grill with a person putting vegetables on top of them.\n",
  "258911": "A woman in a straw hat takes photos of brown cows inside a barn.\n",
  "259097": "A man jumps to catch a Frisbee flying through the air.\n",
  "259382": "A giraffe stands with it's front legs spread apart.\n",
  "259571": "There are man lining the sides of the dumb truck.\n",
  "259597": "A young boy is recording a performance on a cellphone of several people.\n",
  "259625": "An elephant walks around a fenced in area. .\n",
  "259640": "A tamale truck is in a rural city scene.\n",
  "259690": "A man in a wheel chair who is holding a baseball bat.\n",
  "259830": "A building has many bikes pared outside of it.\n",
  "259854": "A view of several billboards and two traffic signs on one pole. .\n",
  "260105": "an image of a table setting with a breakfast platter on it.\n",
  "260106": "A person sitting on a horse in air over gate in grass with people and trees in background.\n",
  "260261": "A man cutting a cold coconut on the back of a truck.\n",
  "260266": "A street light on a street corner with cars driving on it. .\n",
  "260470": "A row of several types of pastries on display.\n",
  "260657": "two signs that are advertising a mexican restaurant.\n",
  "260925": "The cat is laying on the hood of the car. .\n",
  "261036": "Child throwing Frisbee on a field with cones and people in the background. .\n",
  "261061": "A girl throwing a boomerang in a backyard.\n",
  "261097": "Male tennis player on the middle of the court.\n",
  "261116": "People and dishes from cake at a children's party.\n",
  "261161": "A big dog on a leash, sitting next to a pink painted bench.\n",
  "261318": "A man on his phone is on a red bench.\n",
  "261535": "A female tennis player lifting up her skirt.\n",
  "261706": "A black and white cat rests on a couch on top of a remote control.\n",
  "261712": "Two giraffes standing on a dirt path in a fenced in area with trees and green grass surrounding them.\n",
  "261732": "A man jumping up on a blue tennis court with a black tennis racket in his hand. .\n",
  "261796": "a house is sitting on an empty block.\n",
  "261888": "a bicyclist rests on a bike on an empty highway with two horses walking alone up the street .\n",
  "261982": "a person on a skate board does a trick .\n",
  "262048": "a couple of people lay under an umbrella on a beach .\n",
  "262227": "Part of a computer screen in front of a laptop.\n",
  "262440": "A white bathroom with all of the necessities.\n",
  "262487": "A group of men on a field playing baseball.\n",
  "262587": "A single surfer is catching a small waves.\n",
  "262631": "A large glass jar sitting on a table .\n",
  "262682": "A kitchen interior with olive green wooden cabinets.\n",
  "262895": "Elderly  gray haired man in a suit scowling into the camera.\n",
  "262938": "Two stuffed animals are posed on an open book.\n",
  "263068": "a person riding a skate board at a skate park.\n",
  "263299": "A train riding along the tracks through the woods.\n",
  "263403": "A surfer reaches the peak of a wave.\n",
  "263425": "A hunk of something being brushed with a broom.\n",
  "263463": "a reflection of a dog looking out a window in a side view mirror .\n",
  "263474": "An ordinary bathroom with a toilet and trash bin.\n",
  "263594": "A bird near a car parked at the bay.\n",
  "263644": "An odd bed sits near two separate windows.\n",
  "263679": "A man holds strings connected to a large parachute or kite on the beach.\n",
  "263796": "A dirty old red toilet next to many wires.\n",
  "263860": "Two elephants standing in a field going nose to nose.\n",
  "263966": "A picture of a horse taken through a circular window.\n",
  "263969": "A bride and groom cutting a wedding cake.\n",
  "264335": "A brown, white and black bird flying in blue sky.\n",
  "264441": "A cat is sleeping in a chair with its leg curled around its head. .\n",
  "264535": "man sitting on a bench in the park.\n",
  "264968": "a baseball player standing in the grass with a bat in his hand .\n",
  "265108": "A brick wall with a balloon, luggage and umbrella next to it.\n",
  "265518": "A plate with food on it, a mug, and a fork. .\n",
  "265777": "a woman in a red top some glasses and a pizza.\n",
  "265816": "A man in a horse drawn carriage parked in front of a stone building.\n",
  "266082": "A fire hydrant waits in front of a tall building.\n",
  "266206": "Outside shot of a restroom showing the door partially open.\n",
  "266400": "A line of motorcycles backed in and parked in a line at the edge of a sidewalk.\n",
  "266409": "A man that has ski's and is standing in the snow.\n",
  "266768": "A group of people gather at a picnic table beneath a tree.\n",
  "266892": "Woman wearing white playing tennis with a partner.\n",
  "266981": "People sit and walk around a large hotel parking lot.\n",
  "267169": "A person reading a brown elephant a bottle filled with milk.\n",
  "267191": "people riding on the backs of some elephants .\n",
  "267300": "A tan dog eating food scraps from a plate.\n",
  "267351": "Two clocks on perpendicular facades of a church bell tower.\n",
  "267434": "A herd of cows are by a brick house.\n",
  "267537": "A group of young women sitting next to each other under an umbrella.\n",
  "267670": "A bathroom with a modern white pedestal sink.\n",
  "267903": "A filthy bathroom has a dirt covered sink and a rusty toilet.\n",
  "267933": "A line of horses are walking around a river.\n",
  "267940": "A small ferry docked on calm water in Norway.\n",
  "267946": "A blue sign that is pointing to the restrooms.\n",
  "268000": "a big train passes under a big bridge .\n",
  "268375": "A goup of elephants in an enclosed area with a lot of trees behind them.\n",
  "268378": "A group of people sitting around a table with food and drink.\n",
  "268729": "Zebras, wildebeests, and a giraffe stand in a zoo enclosure.\n",
  "268831": "A bathroom that has a be-day next to the toilet.\n",
  "268996": "A green street sign handing from a black pole with a building in the background.\n",
  "269113": "A pack of dogs are playing outside in the grass.\n",
  "269121": "A man playing tennis throws the ball in the air.\n",
  "269196": "A knot of sheep are huddled close and looking out of a barbed wire fence with a frost-covered landscape behind them. .\n",
  "269314": "A cat resting in the top of a palm tree on a clear day.\n",
  "269316": "A bunch of men are running to catch the frisbee that is thrown.\n",
  "269632": "a public transit bus on a city street.\n",
  "269682": "Traffic lights and camera under a stormy sky.\n",
  "269866": "Chrome colored toaster oven with time on 10.14.\n",
  "269932": "A large red chair has a horse statue on it.\n",
  "269942": "A green traffic light hovering over a street.\n",
  "270066": "A white motorcycle parked next to a sidewalk.\n",
  "270122": "A surfer in the middle of two waves that have crested.\n",
  "270244": "A half zebra hybrid is standing in tall grass.\n",
  "270297": "A train engine approaches a switch in a train yard.\n",
  "270386": "A one way sign and two other signs mounted to a pole.\n",
  "270402": "Two elephants standing in a pen in different spots.\n",
  "270474": "A child looks on in amusement while holding a baseball bat. .\n",
  "270677": "A boy posing for a picture with his skateboard.\n",
  "270705": "an orange white and black bird and a curtain.\n",
  "270883": "A woman lays on a bed in her underwear.\n",
  "270908": "A male tennis player lays on the ground.\n",
  "271116": "The men sit at a table with their phones in their hands.\n",
  "271402": "Two cute girls with a scooter and tennis raquet.\n",
  "271457": "A bench right next to some tall grass at the edge of a body of water.\n",
  "271471": "A bunch of bananas is displayed on a counter top.\n",
  "271728": "A cat lying on a sofa in front of a computer.\n",
  "271997": "A portrait picture of a young man in a suit and tie.\n",
  "272049": "A yellow truck is parked on grass near a jumbo jet on display.\n",
  "272136": "An air hanger with an old fighter plane inside.\n",
  "272148": "A group of people swim in shallow ocean waters.\n",
  "272212": "two black and white cows on a green hill.\n",
  "272364": "Four giraffes are reaching in the tree for food.\n",
  "272416": "A very low toilet that is blue and white on a brown floor.\n",
  "272566": "A couple of people sitting next to piles of fruit.\n",
  "273132": "An old woman sitting on a bench next to a fence.\n",
  "273198": "a fire hydrant that has dirty, brown water inside.\n",
  "273232": "A windsurfer and a dog walk along an ocean beach.\n",
  "273420": "A room with a man in it talking on his phone.\n",
  "273493": "tHERE ARE TWO MEN PLAYING TENNIS ON THE TENNIS COURT.\n",
  "273551": "A row of motorcycles parked on the side of a road.\n",
  "273617": "A light shining on the street at night time.\n",
  "273642": "A dog laying on its side with a remote control under its paw.\n",
  "273711": "Many containers of food are on the table.\n",
  "273712": "A large red fridge is sitting on the red carpet. .\n",
  "273715": "The skier is happy to have won the race.\n",
  "273760": "a man that has a tennis racket in his hand.\n",
  "274066": "An instructor is teaching the little girl how to surf.\n",
  "274219": "Talk about a bad hair day, his is frightful.\n",
  "274272": "A large red bus driving in heavy traffic.\n",
  "274411": "woman in tennis garb preparing to serve tennis ball.\n",
  "274460": "A group of young people gather with surfboards on a tropical beach.\n",
  "274687": "A bicycle leaning against a bed in a bedroom.\n",
  "274708": "A group of people on the steep slope of a mountain.\n",
  "275058": "A windsurfer glides across choppy seas in the glistening sun. .\n",
  "275198": "A group of people around a metal table with umbrellas.\n",
  "275392": "A woman on a horse smiling in a green grass.\n",
  "275727": "a yellow and gray train some tracks and trees.\n",
  "275749": "Group of people standing around computer monitors. .\n",
  "275791": "A blue and yellow train is traveling down the tracks near some water and boats.\n",
  "276018": "A group of children carrying stuffed animals walks across the grass. .\n",
  "276024": "a few people that are riding some horses .\n",
  "276055": "A young woman holding a freshly pulled carrot up in the air.\n",
  "276284": "A lone motorcycle is parked in the lighted parking lot.\n",
  "276285": "pizza an other food on a table at a restaurant.\n",
  "276434": "a person that is cutting a cake on a tasble.\n",
  "276707": "A close-up of a street sign with small shops in the background. .\n",
  "276720": "A stone building with a blue door on it.\n",
  "276804": "Players are in the middle of a Baseball game with Old Glory present in the background. .\n",
  "276921": "Two stuffed teddy bears hanging from a rear view mirror.\n",
  "277005": "A man crossing the street in front of a bus stop.\n",
  "277020": "Asian businessman in a restaurant with one of them being served. .\n",
  "277051": "Two birds perched on a table near a plate of food.\n",
  "277197": "A large living room area features a white couch and a glass table.\n",
  "277584": "A cat as sitting outside while looking through a window.\n",
  "277689": "A fancy desert on a table with a number of drinking glasses.\n",
  "278006": "A grey house sitting between a couple of other houses.\n",
  "278353": "A sheep with short hair stands under a fence.\n",
  "278463": "A view of a laptop sitting on a desk with clutter around it.\n",
  "278705": "Two young men riding skateboards on a street next to a graffiti covered wall.\n",
  "278749": "a man holds a sign advertising a deli .\n",
  "278848": "A bunch of people standing together with some umbrellas.\n",
  "278973": "A man in a wet suit is surfing.\n",
  "279145": "A white cat sitting before a bench surrounded by plants in planters.\n",
  "279278": "The man is riding his skateboard down the street. .\n",
  "279541": "A buffet display case filled with lots of pizzas on pans.\n",
  "279714": "The picture of a pin has a huge bat in the background beside a building.\n",
  "279730": "The diners are enjoying their filled  beef sandwiches,.\n",
  "279769": "a banana some papers and a pencil on a wooden table.\n",
  "279774": "a little league baseball game in progress, player swinging the bat.\n",
  "279887": "there are many different bikes that are on display.\n",
  "279927": "PERFORMERS DOING A SHOW IN FRONT OF SPECTATORS.\n",
  "280325": "A parking meter in front of a wall that has been written on. .\n",
  "280710": "People walking on the sidewalk of a city with a tour bus in the background.\n",
  "280779": "A cross country skier in the falling snow.\n",
  "280891": "a person leaning on a bunch of oranges and apples.\n",
  "280918": "Two woman poses while taking a turkey out of the oven.\n",
  "280930": "Little girl laughing and holding a pan of food .\n",
  "281032": "A man with his hair tied back prepares food. .\n",
  "281179": "A bright city street with a stop light and a big Christmas tree.\n",
  "281409": "A baseball player swings his bat while the umpire and referee wait behind him.\n",
  "281414": "A girl is sitting on a brick wall using her cell phone.\n",
  "281447": "A tan horse with a blond mane inside of a coral.\n",
  "281687": "The woman uses her cell phone near many others standing on the sidewalk.\n",
  "281693": "an airline with airplanes from one world parked on the air field.\n",
  "281754": "A young boy holds an umbrella for a girl.\n",
  "281759": "Five ladies standing in the street with umbrellas.\n",
  "281929": "A man standing outside a building holding a bicycle. .\n",
  "282037": "A full view of some baseball players in the field.\n",
  "282046": "A photo of a bench in the middle of the beach.\n",
  "282296": "A fridge stands in the corner of a room. .\n",
  "282298": "a large crowd of people walking through town near a large clock display with a christmas tree in the background.\n",
  "282912": "A giraffe is standing near a rock with green bushes in the background.\n",
  "283037": "A stoplight with a speed radar on top.\n",
  "283038": "a old rusty stop sign out sign some buildings.\n",
  "283070": "The fresh oranges are cut up on the table outside.\n",
  "283113": "A plate of hot dog on a table with a glass.\n",
  "283268": "Parent serving a plastic hot dog in a bun to their child during play.\n",
  "283318": "A store on the corner with an American flag flying from it's side.\n",
  "283412": "a close up of a dog next to a news paper on a table.\n",
  "283520": "Two guys in the woods playing with a disc.\n",
  "283717": "A kitchen counter with a microwave and a toaster oven on a shelf .\n",
  "283785": "Two men dressed as animals entertaining a group of children.\n",
  "284106": "A very nice looking tray filled with some tasty looking food.\n",
  "284279": "A small bird contemplates how to get some seeds.\n",
  "284282": "A GREEN TABLE WITH A OLD RUSTY BLENDER AND A PRINTER .\n",
  "284296": "Giraffes leaning down to drink at a watering hole.\n",
  "284445": "a number of people walking on a side walk.\n",
  "284623": "Black cat with green eyes sitting in a bathroom sink. .\n",
  "284698": "A man taking a picture in a side car mirror with his cell phone.\n",
  "284725": "A bus in China is parked along a curb. .\n",
  "284743": "A woman holding a baseball bat having her photo taken.\n",
  "284762": "Stop light in a city next to a street sign on during the day. .\n",
  "284764": "Man sitting at a table holding eating utensils in his hands over his food. .\n",
  "284991": "A man is drinking water from a red bottle.\n",
  "285047": "A man with a cup of coffee and a cell phone.\n",
  "285349": "A clear heart shaped jar filled with many colors of paper cranes.\n",
  "285788": "Two giraffes and an ostrich at a zoo enclosure habitat.\n",
  "285894": "A group of children looking at two giraffes in an enclosure.\n",
  "286182": "a man sitting in a room with a food on a table.\n",
  "286422": "Two people and a dog are on a sailboat.\n",
  "286458": "Luggage on the floor opened to show it's stuffed contents.\n",
  "286503": "an elephan standing around next to some people .\n",
  "286507": "a train in a rural area covered with heavy snow.\n",
  "286523": "The man in a red hat is listening on his cell phone. .\n",
  "286553": "a couple sitting at a table with a couple of pizzas .\n",
  "286660": "A woman holds a stuffed animal to her face.\n",
  "286708": "a cat wearing a hat on its head .\n",
  "286849": "Four giraffes sticking their heads through a hole in some large rocks.\n",
  "286907": "A bathroom has some blue walls and toilet.\n",
  "286908": "A bunch of images of some tasty looking food.\n",
  "286994": "A group of elephants with water in front and trees behind.\n",
  "287291": "The cars at the intersection are waiting for the pedestrians to cross.\n",
  "287347": "A person making thin crust pizza in a kitchen.\n",
  "287527": "two people standing side by side smiling and one wearing a tie.\n",
  "287545": "A large and small giraffe are looking at something while standing next to a log.\n",
  "287649": "A kitty cat looks up from a desk, near a keyboard.\n",
  "287667": "Oranges and onions shaped to look like a person's face. .\n",
  "287714": "A clean hotel bathroom is pictured in this image.\n",
  "287874": "People are waiting beside the blue train pulling beside the platform. .\n",
  "287959": "This cross section of a sandwich is still wrapped.\n",
  "288042": "A man holding an umbrella next to a waterway.\n",
  "288062": "a toilet with an unusual green seat and back.\n",
  "288391": "a large gold cellphone is on a wall.\n",
  "288430": "A young woman standing on a sandy beach.\n",
  "288584": "A person with a giraffe costume greets people coming through the gate.\n",
  "288685": "A man standing next to a herd of white sheep.\n",
  "288762": "A fresh-looking salad on a square plate. .\n",
  "288862": "a man standing on one hand holding onto a skateboard .\n",
  "288882": "Two giraffes are standing next to each other.\n",
  "289059": "a man leaning over waiting for a tennis ball to hit .\n",
  "289222": "The light shows safe for animal crossing on the street.\n",
  "289229": "The male doctor is holding a medical saw.\n",
  "289343": "A person rides a bike on the road.\n",
  "289393": "A display of vintage animal toys on the floor.\n",
  "289415": "Large assortment of baked pizzas on counter ready for consumption.\n",
  "289417": "A young person on skis posing for a picture.\n",
  "289516": "A clock set to twenty after three in a field.\n",
  "289586": "Giraffe trying to reach some leafs on a tree.\n",
  "289594": "An old man that is leaning against a pole right by the corner.\n",
  "289659": "Giraffe resting while standing in the dirt and grass.\n",
  "289702": "A black dog sitting next to a mirror and pail.  .\n",
  "289741": "Beautiful view of two cruise ships at dock.\n",
  "289938": "A hot dog vendor sits outside a famous building in the city.\n",
  "289960": "A man is flying a kite at the beach.\n",
  "289992": "A bathroom with white appliances and orange walls.\n",
  "290081": "A pile of orange sitting in a blue bowl.\n",
  "290163": "a young girl making a plate of food .\n",
  "290179": "An aerial view of the city of London on a cloudy day.\n",
  "290248": "Several people are grouped together in a public area.\n",
  "290293": "this train station has many lights on the ceiling.\n",
  "290592": "this is a group of sheep on the grass.\n",
  "290619": "A banana laying next to a plastic container with lid.\n",
  "290768": "A kitchen with sunshine shining off of black and white tiles.\n",
  "290771": "A living room set is displayed next to a large window with a view of a wooded area.\n",
  "290833": "Two zebras graze in a field of short grass.\n",
  "290843": "Cat staring at laptop screen as owner is online.\n",
  "291490": "A cat laying on a blanket on top of a pillow. .\n",
  "291551": "a guy riding his skateboard near the edge of a pool .\n",
  "291619": "A man leaping up to catch a frisbee with another man running behind him.\n",
  "291634": "Bicycles lined up on the side of the road.\n",
  "291664": "A dog standing next to a fire hydrant on a green grass covered park.\n",
  "291791": "A group of people look at the dark green motorcycle parked on the grass.\n",
  "291861": "A lone Zebra near a rock with large rock face in background.\n",
  "292005": "Bright orange bathroom with spackling on the walls.\n",
  "292024": "a woman looking a pizza with assorted toppings .\n",
  "292060": "This is a picture of a white and black kitchen.\n",
  "292082": "A man and child pose for a picture together.\n",
  "292155": "the sun peeking through a colorful umbrella next to a palm tree .\n",
  "292225": "Two people are playing tennis in an outside court.\n",
  "292236": "Several people waiting on the side of train tracks as a train with it;s lights on comes down the track.\n",
  "292330": "A dog on a baseball field playing with a baseball bat.\n",
  "292415": "A man riding a skateboard up the side of a ramp.\n",
  "292446": "A man leaning his head in a box of pizza with some pizza in his mouth.\n",
  "292456": "A man and woman on a scooter receiving baggage from a bellhop.\n",
  "292488": "A person I. A hood jacket capturing a photo using a flip phone .\n",
  "292908": "there is a surfer at the beach riding waves in the ocean.\n",
  "292997": "Car hit on a traffic signal in a road full of snow.\n",
  "293044": "an image of a school approved lunch in a tray.\n",
  "293071": "A fire hydrant painted in the American patriotic colors.\n",
  "293200": "There are many people on this field flying kites.\n",
  "293245": "A motorcycle parked outside the doors of a building .\n",
  "293300": "Looking up at elephants in an enclosure at the zoo.\n",
  "293324": "A group of planes near control tower in an airport.\n",
  "293390": "A vanity stink area with a marble counter top and wooden cabinets.\n",
  "293474": "A yellow fire hydrant on a sidewalk by a storefront.\n",
  "293625": "Young women holding remote game controls while playing.\n",
  "293794": "An older businessman standing by bunches of bananas.\n",
  "293804": "a comfortable living room with brown leather couches and a fireplace.\n",
  "293858": "A chicken Parmesan sandwich with a salad and a glass of water.\n",
  "294162": "The computer mouse is in front of the laptop.\n",
  "294163": "A tall clock tower and a tree against a blue sky.\n",
  "294350": "A man standing in a kitchen preparing food next to other cooks.\n",
  "294695": "Two women leaving a beach with kites flying in the background.\n",
  "294783": "A large room with wooden floors and a bookshelf.\n",
  "294831": "Two slices of chicken pizza on a plate.\n",
  "294855": "A suitcase sitting next to a bottle of champagne.\n",
  "295138": "a person riding a skate board on a ledge.\n",
  "295231": "the seven sheep are preparing to be sheered.\n",
  "295316": "Several people on surfboards who are riding a wave.\n",
  "295420": "Blue truck rolling down the side of a city street. .\n",
  "295478": "A woman with headphones in walking her white dog.\n",
  "295713": "A woman sitting on a bench near a statue, checking her phone.\n",
  "295797": "The top of the clock tower with a weathervane. .\n",
  "295809": "an empty street with a bike lane .\n",
  "296222": "A man is sitting in a hospital room with a piece of pizza on a plate.\n",
  "296224": "A close up view of a very big pretty city bus.\n",
  "296231": "A television is sitting in a cluttered room.\n",
  "296284": "An assortment of doughnuts are arranged in a display case.\n",
  "296317": "Some giraffes in a field near some mountains. .\n",
  "296634": "Three white trays on a countertop containing various types of food.\n",
  "296649": "A view of motorcyclists riding their bikes through heavy city traffic.\n",
  "296657": "Six adult males outside jumping up in the air.  .\n",
  "296969": "A group of giraffes standing in dirt field with trees in background.\n",
  "297022": "An old truck in the field with three men.\n",
  "297084": "a woman in a bathrobe is eating a meal.\n",
  "297085": "a cat is standing in front of a television.\n",
  "297147": "This is a motorcycle that is parked near a building. .\n",
  "297343": "A stop sign standing up against a wall.\n",
  "297353": "A guy with a nice guitar standing on a bed.\n",
  "297396": "A set up small chocolate cakes decorated like trains.\n",
  "297427": "A burger with a doughnut for the bun.\n",
  "297562": " A baby getting a hair cut in the salon sitting in the chair.\n",
  "297578": "A man lighting a cigarette as he walks on a city street.\n",
  "297595": "The surfers is surfing against a high wave.\n",
  "297681": "a car driving through a very flooded street.\n",
  "297698": "A man flying through he air while riding .\n",
  "297830": "happy dog poses outside a door with root beer bottle.\n",
  "298251": "A field full of zebras on a savannah grazing.\n",
  "298396": "A kitchen filled with appliances dishes and a bowl of fruit.\n",
  "298697": "a vast, grassy field with animals in the distance.\n",
  "298738": "A large panda sitting and eating a bamboo plant.\n",
  "298904": "There is a vase filled with water that has rocks and a plant in it.\n",
  "298994": "some different vegetables laid out on a wooden pallet.\n",
  "299355": "A plate topped with broccoli and vegetables on a table.\n",
  "299553": "A crowd of people gathering and flying kites.\n",
  "299609": "A horse in a grassy field set against a foggy mountain range.\n",
  "299720": "A giraffe standing next to a building near a tree.\n",
  "299887": "A man and a woman posing in front of a motorcycle.\n",
  "300039": "A person showing a picture on their cellular phone. .\n",
  "300155": "A bird is sitting on a tree branch spreading its tail-feathers.\n",
  "300233": "A table with a blender, oil and several seasonings. .\n",
  "300276": "Two women standing behind table with cupcakes, cake and a warmer.\n",
  "300341": "Two men play the Nintendo Wii console while others watch.\n",
  "300659": "A sky view of several planes flying in formation in the sky.\n",
  "300842": "a person that is standing on a skateboard.\n",
  "300913": "A kitten is laying on a green throw pillow.\n",
  "301061": "There is an elephant in side a truck trying to come out.\n",
  "301135": "A group of women sitting on a bench near a light pole.\n",
  "301376": "A street corner with traffic lights and cars.\n",
  "301421": "A computer is sitting on a computer desk.\n",
  "301563": "The man is skiing down the snowy slopes.\n",
  "301718": "Two people sitting at a table eating.  .\n",
  "301867": "Three young women smile brightly together under a large umbrella.\n",
  "301981": "A giraffe standing in his enclosure at the zoo.\n",
  "302030": "The desk with a laptop has papers strewn all over it.\n",
  "302107": "A baseball player in a black jersey swinging a bat.\n",
  "302165": "Cows resting in fresh straw bays at a rodeo.\n",
  "302452": "A giraffe drinking from a bottle in front of a group of people.\n",
  "302536": "A man playing a game with a wii controller in a living room.\n",
  "302760": "A bathroom sink with a bottle of hand soap .\n",
  "302882": "A man who is taking a picture with his cell phone.\n",
  "302990": "A man is using his board to surf a wave.\n",
  "303305": "Red and white bus parked at the curb of a street under blue sky.\n",
  "303499": "two men in red coats riding horses in front of a palace.\n",
  "303566": "Boxes of fruit displayed at an open air market.\n",
  "303653": "A woman riding a horse and looking at her reflection in a mirror.\n",
  "303713": "a male tennis player in a white shirt .\n",
  "303818": "A fish eye view of a bus rounding a curve on a city street.\n",
  "303863": "A railroad train rides down the tracks near buildings. .\n",
  "303893": "Two cute children are sitting on the sidewalk eating.\n",
  "303908": "An empty wooden bench near the waters edge.\n",
  "304180": "Three women, one with a skateboard outside a store.\n",
  "304291": "a horse that is walking around a field.\n",
  "304365": "this is a train station waiting for a passenger.\n",
  "304396": "a big building with a clock at the top of it .\n",
  "304404": "A batter swings the bat as the crowd watches attentively.\n",
  "304545": "A black bag attached to the long handle of a piece of luggage.\n",
  "304560": "A black cat is staring directly into the camera. .\n",
  "304812": "A person carrying a surfboard on the beach at sunset.\n",
  "304817": "Snowboard atop of wooden structure next to evergreen plant.\n",
  "304984": "A toasted sandwich with sliced fruit and a fork.\n",
  "305309": "Two young boys in a black and white picture are playing baseball.\n",
  "305317": "A bunch of people are holding kites and the wind is blowing them on a grassy field.\n",
  "305343": "two cup like things with a bird and a wolf painted on them.\n",
  "305609": "Various plates of food that include hashbrowns, waffles and grits.\n",
  "305695": "A bunch of zebras grazing near a road where vehicles are driving by.\n",
  "306136": "A bus parked outside and below an illuminated Apple sign.\n",
  "306139": "Seven people seated at table talking and working on computer devices.\n",
  "306437": "The man is practicing his moves on his skateboard.\n",
  "306582": "Washed clothing is hung out on a clothesline in a cattle enclosure. .\n",
  "306700": "A woman getting ready to eat a pizza on the table.\n",
  "306733": "A bathroom with a sink, towel rack and shower stall.\n",
  "306893": "A red and white train near a terminal in a city setting.\n",
  "307074": "A city intersection with traffic lights on a stormy day.\n",
  "307145": "A KITCHEN WITH A SINK AND TABLE IN IT .\n",
  "307172": "Flat pizza like object sitting on table with a person taking a slice.\n",
  "307598": "A yellow and green train is coming down the track.\n",
  "307658": "a picture of a grizzly bear in the wild.\n",
  "308165": "A boy is jumping his skateboard over an orange cone.\n",
  "308193": "There is a clock on the side of a clock tower.\n",
  "308328": "a group of people that are next to some bags.\n",
  "308391": "Sign of Arch Street Fire Department saying \"He who laughs last thinks slowest\".\n",
  "308394": "A woman with a cane and shopping bag sitting.\n",
  "308430": "A skillet on a stove with vegetables in it .\n",
  "308466": "A bathroom with a sink, toilet, tub and shower head.\n",
  "308476": "Polar bear licking rock near ball and fence.\n",
  "308531": "A red clock tower towering over a lush green park.\n",
  "308545": "A young boy in riding clothes rides a horse.\n",
  "308587": "People are windsurfing near a beach on a cloudy day.\n",
  "308631": "a group of people gathered around an old dirty vintage motorcycle.\n",
  "308753": "A cave is situated in a rocky wall.\n",
  "308793": "A person walking in the snow with skis on their back.\n",
  "308799": "A kitchen with hardwood floors and a sink and oven.\n",
  "309173": "A red and white traffic sign attached to a pole in a city.\n",
  "309391": "Vehicle traffic on a hilly street in a small town.\n",
  "309452": "A yellow and black bird is perched on a tree. .\n",
  "309467": "two people walking up the hill so they can ski down it.\n",
  "309484": "A dog is laying down and getting his teeth brushed.\n",
  "309495": "A blurry photo of a toilet seat in a bathroom.\n",
  "309655": "A woman stands on skis on a snowy hill.\n",
  "309678": "Woman holding tomato over item being prepared for baking.\n",
  "309938": "A dog sits near books with a shirt on.\n",
  "309964": "A pair of friends sit beneath a massive blue umbrella.\n",
  "310072": "Hat sits on empty park bench made of black iron.\n",
  "310200": "A pastry is torn in half on a plate.\n",
  "310622": "A West 32nd sign under a Korea Way road sign. .\n",
  "310862": "A man wearing a gray vest and a red stripe tie.\n",
  "310980": "A person who is sitting and looking up at a computer monitor. .\n",
  "311002": "A pitcher throws a baseball to a batter.\n",
  "311081": "A small bathroom with the shower curtains open.\n",
  "311180": "Someone holding out their hand with a pair of scissors on it.\n",
  "311190": "A dog with a cowboy hat on its head.\n",
  "311295": "many animals in a field with trees and bushes in the background.\n",
  "311303": "A sandwich with salad on a plate and a cup of pop.\n",
  "311392": "a dairy cow standing in a stall full of hay.\n",
  "311394": "A baby holds a toothbrush in its hand.\n",
  "311518": "Row boat sitting in the middle of a lake by building.\n",
  "311789": "A cat sleeping on a keyboard on a table.\n",
  "311883": "A yellow train engine pulling train cars over road.\n",
  "311909": "A very big white bus parked by the curb.\n",
  "311928": "a small boy with a bat and ball on some grass.\n",
  "311950": "A hot dog with mustard and catchup on it.\n",
  "312192": "A table with a plate that has a pizza on it along with fresh vegetable and meat toppings.\n",
  "312213": "A grey and white cat sits near a laptop.\n",
  "312237": "A sunny day at the beach with a lot of people.\n",
  "312263": "A large building that has a clock on it.\n",
  "312278": "A rack filled with lots of different bags of luggage.\n",
  "312340": "A black and white cat laying in green vegetation.\n",
  "312406": "a table that has some bananas and a cup on it.\n",
  "312421": "A lunch box of some sorts is placed on the table. .\n",
  "312489": "A person using a wind surfboard, on the beach.\n",
  "312549": "A double street sign at a neighbourhood corner.\n",
  "312552": "Woman standing while eating pizza from a plate.\n",
  "312586": "A  bear walking down the grass in the open.\n",
  "312720": "A skier is in the air holding on to some ropes.\n",
  "313034": "A man smiling while standing in front of a woman with a piece of cake. .\n",
  "313130": "A refrigerator up against a wall with a mirror.\n",
  "313182": "A bus sits diagonal from the curb next to a building and people.\n",
  "313454": "A man is speaking at a panel in front of a crowd.\n",
  "313562": "A woman standing in a kitchen touching a pile of carrots.\n",
  "313588": "A woman standing on a cobbled street holding a pink umbrella. .\n",
  "313783": "Two burgers sit on a plate next to carrots and potatoes.\n",
  "314034": "A herd of cattle is near a flock of birds swimming in the water.\n",
  "314177": "A picture of the photographer sitting on the toilet .\n",
  "314182": "a close up of a bowl with vegetables with broccolli.\n",
  "314251": "A group of scooters rides down a street.\n",
  "314264": "A man refreshing fake flowers in vases on a crypt wall.\n",
  "314294": "An elephant walks alone past some big rocks boulders in an open field.\n",
  "314541": "An empty blue park bench on a slight hill.\n",
  "314709": "A guy is having fun skiing down the slope of the hill.\n",
  "314914": "there are many different signs on the same street pole.\n",
  "315001": "An ocean view with dozens of birds in the sky.\n",
  "315187": "Traffic in front of Walgreens on a town street.\n",
  "315219": "a white phone cord and a phone and its phone wire.\n",
  "315257": "A bird is sitting on a bowl of birdseed.\n",
  "315450": "Street traffic, view of an Alamo Bus, a Gold Coast Tour bus and several cars.\n",
  "315492": "A little girl plays at changing her teddy bear's diaper.\n",
  "316015": "A cat sits on a computer desk next to a keyboard.\n",
  "316054": "A train blowing smoke is coming down the tracks.\n",
  "316404": "Two men posing for a picture in a tennis game in a funny way.\n",
  "316666": "Flowers that are in a vase on a table.\n",
  "317024": "A zebra standing over a puddle in an enclosure.\n",
  "317433": "A man behind farm equipment pulled by horses.\n",
  "317999": "A  girl reading a book on a bed next to a man.\n",
  "318080": "Two brown bears growling at each other while laying on a log.\n",
  "318114": "The dessert is next to a glass of orange juice.\n",
  "318138": "A girl playing a video game with several other people nearby.\n",
  "318238": "Three dogs are sleeping across the length of the bed.\n",
  "318455": "Half a cake and two plates of cupcakes on a table.\n",
  "318908": "Cute little dog poses for a picture with the top of it's head dyed.\n",
  "319100": "Two people sitting together on a couch playing wii.\n",
  "319184": "some players are playing frisbee on a grass field.\n",
  "319369": "PEOPLE STANDING NEAR A GUARD IN FRONT OF A RENTAL STORE.\n",
  "319534": "A boy standing in the door of a bus.\n",
  "319607": "A traffic light on the intersection of a city, with a large building and a bicyclist in the background.\n",
  "319617": "A hotdog with mustard and ketchup on a white oval plate.\n",
  "319696": "a microwave sits on top of a counter .\n",
  "319721": "A woman hold a brown horse while a woman watches.\n",
  "319935": "A bedroom suite with balcony and  lovely view.\n",
  "320232": "A picture of a public parking booth. .\n",
  "320425": "A group of giraffes are gathered together in their enclosure.\n",
  "320490": "A boy swinging a baseball bat at a ball.\n",
  "320554": "There is a cat lying in the sun by the bench.\n",
  "320632": "A group of zebras are standing together in the grass.\n",
  "320642": "two women holding remotes playing a game .\n",
  "320664": "Traditional American comfort food arranged on a plate.\n",
  "320696": "Surfer riding out end of wave with large breaking wave in background.\n",
  "320706": "The blender is full all the way to the top.\n",
  "320743": "Boys with wide hats are riding elephants on the dirt.\n",
  "321118": "A open laptop with a mouse beside it.\n",
  "321214": "Baby boy at the table eating cake frosting off his hand.\n",
  "321333": "two children one holding a bear and one holding a cell phone.\n",
  "321557": "A motorcycle parked next to a white building.\n",
  "321790": "A man holding a tennis racket at the tennis courts.\n",
  "321887": "a white sheep against a colored background orange blue purple and yellow.\n",
  "322163": "Cooks are gathered preparing a meal in the kitchen.\n",
  "322211": "A box of pastries is sitting on a table.\n",
  "322352": "A fireplace and dining table in a dining room.\n",
  "322429": "a shelf that has a bunch of glass items on it.\n",
  "322574": "French fries and a bag with bread sticking out .\n",
  "322610": "A woman holding an umbrella stands as people walk past.\n",
  "322724": "A man is standing on a snowy hills with his skiis.\n",
  "322829": "A BENCH IS SEATED ON THE GRASS .\n",
  "322844": "A teddy bear and a stuffed fish set next to each other.\n",
  "322864": "Two guiding signs are pictured in front of a busy street.\n",
  "322895": "A room with a full wall of windows with multiple sofas and chairs.\n",
  "322944": "A young woman with bruised face and bloody now holding a stuffed animal mouse in her arms.\n",
  "322959": "A selection of breads, meat, spreads, and cheeses. .\n",
  "322968": "A large green building with a clock at the top of it .\n",
  "323151": "A beer sits untouched on a table with other food.\n",
  "323202": "White toilet in a restroom with three seashells on the tank.\n",
  "323263": "A woman is selling fruit in a poor neighborhood.\n",
  "323355": "A boy with a fedora on holding a pizza box open.\n",
  "323496": "A LITTLE BOY PLAYING A GAME OF TENNIS .\n",
  "323571": "A street sign sitting on the side of a large pole.\n",
  "323709": "An airplane is parked next to a domed tower.\n",
  "323751": "A passenger train that is traveling down railroad tracks.\n",
  "323799": "a family standing in the yard to take a picture.\n",
  "323828": "A train going along a pair of train tracks.\n",
  "323895": "A man is in action on a green tennis court.\n",
  "324158": "A man walking his dog on a quiet country road.\n",
  "324258": "two men standing in the living room and playing a video game with wii motes.\n",
  "324614": "a woman looking a mirror whiile brushing her teeth .\n",
  "324715": "A laptop computer sits on a desk with scissors.\n",
  "324818": "Two parrots perching on a tree branch in a tropical garden.\n",
  "324927": "A couple of slices of pizza and a glass of drink.\n",
  "325031": "An elephant statue with an opening of various drawings on it.\n",
  "325114": "a little red tabke with a plate on it in the bathroom .\n",
  "325306": "a little zebra biting its own tali .\n",
  "325347": "A tennis player makes a quick shuffle to return the ball.\n",
  "325483": "Two young men are playing a WII video game.\n",
  "325527": "a little brown teddy bear sitting alone on top of a carboard box.\n",
  "325838": "A woman works at a computer workstation in an office.\n",
  "325991": "a man is about to throw a Frisbee in a grassy field.\n",
  "326082": "A living room with a couple of furniture. .\n",
  "326128": "A person standing in the snow near a snow board.\n",
  "326174": "Several people are getting ready to enter the water for surfing.\n",
  "326248": "People on a tennis court with others watching.\n",
  "326462": "A person is holding a doughnut with sprinkles.\n",
  "326541": "People at a public event using cell phones to take pictures of the event.\n",
  "326542": "a man riding skis down a snow covered slope.\n",
  "326627": "A single rainbow is seen between a building and a road sign.  .\n",
  "326970": "Three people are sitting and waiting on a planter.\n",
  "327306": "The boy is riding his skateboard outside alone.\n",
  "327592": "an image of a woman about to eat a slice of cake.\n",
  "327601": "A barefoot woman sitting in a chair relaxing.\n",
  "327605": "A woman on skis standing sideways in the snow.\n",
  "327617": "a vintage photo of a woman with a tennis racket .\n",
  "327701": "A woman hits a tennis ball with some kids.\n",
  "327769": "A cat lying inside a sink with a hair brush, sanitizer and toothpaste on top.\n",
  "327780": "a close up of a piece of cake on a plate.\n",
  "327890": "Three empty benches face each other beneath a canopy.\n",
  "328030": "The stuffed bear is holding a hockey stick  and \"playing\" hockey with them \"watching.\"",
  "328117": "A bunch of doughnuts in a silver pan with serving tongs.\n",
  "328238": "A man in a grassy field about to catch a frisbee.\n",
  "328286": "Boats at the dock with a city backdrop.\n",
  "328337": "A boy preparing to throw a frisbee outside.\n",
  "328430": "a woman reaching up while jumping to hit a tennis ball .\n",
  "328601": "A tennis player gets ready to hit a ball.\n",
  "328683": "A parking meter sitting on the sidewalk in front of a building.\n",
  "328959": "a vintage photo of a toilet sitting next to a shower .\n",
  "329041": "A stack of luggage with an opened one on top.\n",
  "329080": "A hotel room with focus on the two beds.\n",
  "329219": "A man in the kitchen standing with his dog.\n",
  "329319": "A cat sitting on a chair looking down.\n",
  "329323": "The crowd is looking at something covered in white cloth.\n",
  "329447": "Cows in a field being rounded up by a herding dog.\n",
  "329455": "Some people sitting at a table with a large oval shaped pizza.\n",
  "329456": "A group of people walking across asphalt, dressed informally.\n",
  "329542": "Group of decorated cupcakes being filmed on camera. .\n",
  "329614": "A busy street by large Gothic style buildings.\n",
  "329827": "A person in a blue coat is skiing down a slope.\n",
  "330369": "A red fishing boat moving through the water.\n",
  "330396": "A man and a woman standing on a stony beach with driftwood.\n",
  "330554": "A blender on the c9unter that has spilled everywhere.\n",
  "330790": "An elephant wearing a saddle holds leaves in it's trunk.\n",
  "330818": "A young man is standing behind a counter, carefully looking over an array of food preparation equipment and related items. .\n",
  "331075": "A dog enjoying playing on the beach in the sun.\n",
  "331280": "A couple of horses in what appears to be a circus.\n",
  "331317": "A clock set up in front of windows where you can see the shadows of people inside.\n",
  "331352": "Off white toilet with a faucet and controls. .\n",
  "331569": "The strawberries was sitting beside the tall glass of milkshake.\n",
  "331604": "The man is para sailing on the water. .\n",
  "331799": "The woman is handing a package to another person. .\n",
  "331817": "A person is eating food at the table.\n",
  "332318": "A bunch of cattle relax in a pasture located in the mountains.\n",
  "332351": "A lot of people riding boards on top of a wave.\n",
  "332455": "The neon purple toilet with lid lifted is in the bathroom with brown tile. .\n",
  "332570": "A PERSON HOLDING A BLACKBERRY CELL PHONE IN THEIR HAND .\n",
  "332845": "A man sits on his bed with a laptop in his bedroom as a ray of sunlight streams through the window. .\n",
  "332901": "a couple of sheep are in a corral together.\n",
  "333069": "One giraffe is crouched down while another peers out of the shrubbery.\n",
  "333237": "A bedroom with a bed, a dresser, a desk, a mirror, and decorated walls.\n",
  "333402": "Young male boarding a city bus at a bus stop.\n",
  "333697": "A corner with a Stop sign, a no entry sign and a one way sign in front of a brick wall with graffiti.\n",
  "333745": "A woman holding an umbrella and walking beside a bus.\n",
  "333772": "Two black and white cats are on a keyboard.\n",
  "333956": "A parking meter beside a walkway near the water.\n",
  "334006": "Sanitation trucks on roadway in large city area.\n",
  "334309": "A picture of a person eating some food.\n",
  "334371": "Double-Decker buses line up at a bus stop.\n",
  "334399": "A clock that is standing on a table.\n",
  "334417": "A bearded man in a suit eating pizza. .\n",
  "334483": "many people standing near a table with cake.\n",
  "334521": "Two giraffes inside of a cage at the zoo.\n",
  "334530": "A surfer rides his board inside an arching wave.\n",
  "334555": "There is a cow in the middle of a busy road.\n",
  "334719": "A woman and kids on a beach with a large rocky area in background.\n",
  "334767": "people going along a hill on skiis during a race .\n",
  "334977": "We are looking at multiple views of a windows phone.\n",
  "335081": "Stuffed teddy bears and ducks for sale at a stall .\n",
  "335177": "Suburban street scene showing a curve, houses, and cars in driveway.\n",
  "335328": "A young boy on a surfboard being taught to surf.\n",
  "335427": "A bowl full of broth and pieces of broccoli with a spoon and fork.\n",
  "335450": "two horses stand next to each other in front of a fence .\n",
  "335529": "A wooden bench is located by a lakeshore.\n",
  "335658": "A desktop with a white mouse and keyboard.\n",
  "335800": "A street sign with flags and a high rise building in the background.\n",
  "335954": "Pair of fruit cups on kitchen marble counter.\n",
  "336053": "Two small children sit and dine at a table, inside a restaurant.\n",
  "336209": "A person that is doing a trick on a skateboard.\n",
  "336232": "A bus, cars and a motorcycle driving in busy traffic on the street.\n",
  "336265": "A boy is playing with a toy in a grassy field.\n",
  "336309": "The plane is flying high in the sky.\n",
  "336356": "a girl sitting at a table in front of two pizzas.\n",
  "336587": "A stop sign that is attached to a broken wooden pole.\n",
  "336628": "A clown like individual walking off a tram.\n",
  "336658": "A city road with buses and people on the sidewalk.\n",
  "337055": "A woman is sitting with a suitcase on some train tracks.\n",
  "337498": "A plate with a slice of pizza sits on a table.\n",
  "337987": "A brown, black and white bird resting on a tree branch.\n",
  "338191": "a collage with nine fire hydrants of different color combinations.\n",
  "338219": "a close up of some motorcycles parked on a grassy field.\n",
  "338304": "On a narrow street people are taking pictures of sheep.\n",
  "338325": "A plane flies through the sky at an angle. .\n",
  "338428": "A photo of a green truck parked in grass.\n",
  "338532": "A giraffe looking and  walking around a field. .\n",
  "338560": "A fire hydrant on a sidewalk of a city .\n",
  "338624": "A man walks a dog past rows of chairs outside a store.\n",
  "338625": "A city bus that is stopped at a bus stop.\n",
  "338718": "A street scene with the street sign knocked over.\n",
  "338901": "A dog looks up while laying on a blue couch.\n",
  "338905": "a group of people sitting around a long table while eating from plates of food .\n",
  "338986": "a group of cars next to a train.\n",
  "339442": "some fruit is next to a sandwich on a table.\n",
  "339823": "A woman holds an umbrella in the air.\n",
  "339870": "A church steeple is shown amidst telephone wires and lights. .\n",
  "340015": "A pizza with ingredients that include tomatoes and meatballs.\n",
  "340175": "The large room has a wooden table with chairs and a couch.\n",
  "340272": "Three sheep eating grass near a water source.\n",
  "340451": "A person in rubber boots and a rain coat seated on a bench.\n",
  "340697": "Several bottles are displayed in a commercial refrigerator.\n",
  "340894": "A laptop with external keyboard, mouse, phone and photo on a desk.\n",
  "340930": "the scissors sit in a containers with pens and markers.\n",
  "341058": "An umbrella is opened over an outdoor table.\n",
  "341094": "A man poses with a picture of a bear and a car.\n",
  "341196": "A surfer riding through a barrel on a wave. .\n",
  "341469": "The red suitcases are setting in a corner, waiting to be bought for a trip.\n",
  "341681": "A man with a tennis racket is in the air with legs spread apart next to a tennis ball in motion.\n",
  "341719": "Skiers and snowboarders mill about on a mountain.\n",
  "341828": "A MAN IS EATING A TALKING ON THE PHONE .\n",
  "341921": "A boy at a playground, sitting on a bench and reading a book.\n",
  "341973": "two females are holding jelly donuts with a bite taken out .\n",
  "342006": "Water traffic along the Thames by Big Ben.\n",
  "342128": "A man with shorts and long tube socks holds a racket.\n",
  "342186": "A veggie pizza is sitting on a white plate.\n",
  "342295": "Someone put their art collection in their bath tub.\n",
  "342367": "A photo of a television depicts a courtroom.\n",
  "342397": "A young child is hopping from the slope on their skis.\n",
  "342971": "A man reaching out to catch a frisbee.\n",
  "343076": "Cat lying on top of a shelf with its front leg hanging down.\n",
  "343149": "People on a sidewalk next to building with clock.\n",
  "343218": "A man standing on a tennis court holding a racquet.\n",
  "343315": "A red fire hydrant on a street corner near a sign.\n",
  "343453": "A woman is on skis on the ski slope.\n",
  "343466": "A kitchen with a window and bunch of kitchen furniture in it.\n",
  "343496": "A person walking near a stop sign in a residential neighborhood.\n",
  "343524": "A man getting ready to serve a tennis ball.\n",
  "343561": "A large group of people watching a bu g group of bikers go by.\n",
  "343706": "It is winter, and this young woman wearing her cold weaterh coat also has her Smartphone in a handknitted sleeve.\n",
  "343803": "A person on field with a Frisbee in their hand.\n",
  "343934": "A parked blue motorcycle sitting in the corner .\n",
  "343937": "A woman in white jacket snowboarding on snowy hill.\n",
  "343976": "a city sign in the night time with cars passing underneath\n.\n",
  "344029": "A black passenger bus navigating paved city streets.\n",
  "344059": "Two giraffe standing in a field next to trees.\n",
  "344100": "Half eaten sandwich and a cup of coffee sitting on table in front of camera equipment.\n",
  "344268": "United States President Barack Obama gives a speech in front of American and Russian flags.\n",
  "344611": "a street sign mentioning water on the road.\n",
  "344614": "A clock tower with multiple columns in a city.\n",
  "344621": "A living room with a couch, chair and a coffee table.\n",
  "344795": "a pot of food cooking in an oven.\n",
  "344816": "A train is sitting along tracks under and overpass.\n",
  "344888": "A group of horses standing next to each other.\n",
  "344909": "A fire hydrant is standing on the sidewalk with two spouts.\n",
  "345027": "A vehicle and a motor bike on the beach.\n",
  "345252": "a young man sitting in front of a computer screen and laptop wearing headphones.\n",
  "345261": "Two giraffes standing in a wide open area.  .\n",
  "345356": "two males at a table with food and one has a cellphone.\n",
  "345361": "Children gather around the table with party hats on .\n",
  "345385": "A couple of men snuggling on a bed with one under the cover.\n",
  "345397": "A man takes a pictures of himself in a mirror.\n",
  "345466": "A baseball player throws a pitch while others watch from the dugout.\n",
  "345469": "The shelves have on different types of donuts. .\n",
  "345941": "A plate with an ice cream dessert on it .\n",
  "346232": "A group of people are walking and one is holding an umbrella.\n",
  "346638": "A beer is sitting next to a computer.\n",
  "346703": "A person that is putting fire on a cake.\n",
  "346707": "A batch of green banana's next to a large set of red banana's.\n",
  "346905": "Two large brown elephants standing over a small elephant. .\n",
  "346968": "A smiling woman in uniform on a cell phone.\n",
  "347163": "A stop sign with graffiti that reads \"gentrifying georgetown.\"",
  "347174": "A girl is sleeping in a bed with the light on.\n",
  "347254": "A man in a reception hall holds a drink.\n",
  "347265": "A man is walking in skies in the snow.\n",
  "347335": "A large white plate of food on a table.\n",
  "347370": "A hand holds a piece of fruit with the peel cut off.\n",
  "347456": "Two large brown elephants walking in a grassy field. .\n"
}